AutoOrgan/__init__.py
AutoOrgan/backend_data.py
AutoOrgan/config.py
AutoOrgan/fixed.py
AutoOrgan/infer.py
AutoOrgan/main.py
AutoOrgan/postprocess.py
AutoOrgan/postprocess_gpu.py
AutoOrgan/preprocess.py
AutoOrgan-0.1.0.dist-info/LICENSE
AutoOrgan-0.1.0.dist-info/METADATA
AutoOrgan-0.1.0.dist-info/WHEEL
AutoOrgan-0.1.0.dist-info/entry_points.txt
AutoOrgan-0.1.0.dist-info/top_level.txt
AutoOrgan-0.1.0.dist-info/RECORD
