Metadata-Version: 2.2
Name: AutoOrgan
Version: 0.1.0
Summary: A short description of the package
Home-page: https://github.com/yourusername/mypackage
Author: Wang Nannan
Author-email: your.email@example.com
Classifier: Programming Language :: Python :: 3
Classifier: License :: OSI Approved :: MIT License
Classifier: Operating System :: OS Independent
Requires-Python: >=3.6
License-File: LICENSE
Requires-Dist: onnxruntime-gpu
Requires-Dist: scipy
Requires-Dist: scikit-image
Requires-Dist: munch
Requires-Dist: tqdm
Dynamic: author
Dynamic: author-email
Dynamic: classifier
Dynamic: description-content-type
Dynamic: home-page
Dynamic: requires-dist
Dynamic: requires-python
Dynamic: summary
